stimcirq/__init__.py
stimcirq/_cirq_to_stim.py
stimcirq/_cirq_to_stim_test.py
stimcirq/_cx_swap_gate.py
stimcirq/_cx_swap_test.py
stimcirq/_cz_swap_gate.py
stimcirq/_cz_swap_test.py
stimcirq/_det_annotation.py
stimcirq/_det_annotation_test.py
stimcirq/_i_error_gate.py
stimcirq/_i_error_gate_test.py
stimcirq/_ii_error_gate.py
stimcirq/_ii_error_gate_test.py
stimcirq/_ii_gate.py
stimcirq/_ii_gate_test.py
stimcirq/_measure_and_or_reset_gate.py
stimcirq/_measure_and_or_reset_gate_test.py
stimcirq/_obs_annotation.py
stimcirq/_obs_annotation_test.py
stimcirq/_shift_coords_annotation.py
stimcirq/_shift_coords_annotation_test.py
stimcirq/_stim_sampler.py
stimcirq/_stim_sampler_test.py
stimcirq/_stim_to_cirq.py
stimcirq/_stim_to_cirq_test.py
stimcirq/_sweep_pauli.py
stimcirq/_sweep_pauli_test.py
stimcirq/_two_qubit_asymmetric_depolarize.py
stimcirq/_two_qubit_asymmetric_depolarize_test.py
stimcirq-1.15.0.data/data/README.md
stimcirq-1.15.0.dist-info/METADATA
stimcirq-1.15.0.dist-info/WHEEL
stimcirq-1.15.0.dist-info/top_level.txt
stimcirq-1.15.0.dist-info/RECORD
