Metadata-Version: 2.4
Name: stimcirq
Version: 1.15.0
Summary: Implements a cirq.Sampler backed by stim.
Home-page: https://github.com/quantumlib/stim
Author: Craig Gidney
Author-email: craig.gidney@gmail.com
License: Apache 2
Requires-Python: >=3.6.0
Requires-Dist: stim
Requires-Dist: cirq-core
Dynamic: author
Dynamic: author-email
Dynamic: description
Dynamic: description-content-type
Dynamic: home-page
Dynamic: license
Dynamic: requires-dist
Dynamic: requires-python
Dynamic: summary
